ehelply_generator/__init__.py
ehelply_generator/ehelply_gen.py
ehelply_generator/generator.py
output/__init__.py
output/crud.py
output/models.py
output/schemas.py
ehelply_generator-0.1.2.dist-info/LICENSE
ehelply_generator-0.1.2.dist-info/METADATA
ehelply_generator-0.1.2.dist-info/WHEEL
ehelply_generator-0.1.2.dist-info/entry_points.txt
ehelply_generator-0.1.2.dist-info/top_level.txt
ehelply_generator-0.1.2.dist-info/RECORD
