Metadata-Version: 2.1
Name: ehelply-generator
Version: 0.1.2
Summary: eHelply Generator
Home-page: https://github.com/ehelply/Generator
Author: Shawn Clake
Author-email: shawn.clake@gmail.com
License: UNKNOWN
Platform: UNKNOWN
Classifier: Programming Language :: Python :: 3
Classifier: License :: OSI Approved :: GNU General Public License v3 (GPLv3)
Classifier: Operating System :: OS Independent
Requires-Dist: pytest
Requires-Dist: sqlalchemy
Requires-Dist: pydantic
Requires-Dist: python-slugify
Requires-Dist: ehelply-bootstrapper
Requires-Dist: click
